{
  "parent": "minecraft:recipes/root",
  "criteria": {
    "has_milk": {
      "conditions": {
        "items": [
          {
            "items": "kitchenkarrot:milk"
          }
        ]
      },
      "trigger": "minecraft:inventory_changed"
    },
    "has_the_recipe": {
      "conditions": {
        "recipe": "kitchenkarrot:milk"
      },
      "trigger": "minecraft:recipe_unlocked"
    }
  },
  "requirements": [
    [
      "has_the_recipe",
      "has_milk"
    ]
  ],
  "rewards": {
    "recipes": [
      "kitchenkarrot:milk"
    ]
  }
}